{
  "project_info": {
    "project_number": "576332330827",
    "project_id": "upload-9fc1b",
    "storage_bucket": "upload-9fc1b.appspot.com"
  },
  "client": [
    {
      "client_info": {
        "mobilesdk_app_id": "1:576332330827:android:244f976d6f77565eacdace",
        "android_client_info": {
          "package_name": "com.example.upload"
        }
      },
      "oauth_client": [
        {
          "client_id": "576332330827-ahgdp03d8d99fopgr0e2oajkhlt1snuc.apps.googleusercontent.com",
          "client_type": 3
        }
      ],
      "api_key": [
        {
          "current_key": "AIzaSyC5Awn7jiK8yAVCv6XzfXz0AIPljEOosnM"
        }
      ],
      "services": {
        "appinvite_service": {
          "other_platform_oauth_client": [
            {
              "client_id": "576332330827-ahgdp03d8d99fopgr0e2oajkhlt1snuc.apps.googleusercontent.com",
              "client_type": 3
            }
          ]
        }
      }
    }
  ],
  "configuration_version": "1"
}